{
"nodes":[
{ "name":"Adelcio Carlos de Oliveira", "idlattes":"0487113229071944", "rotulo":"[Sem rotulo]", "collaborationrank":1.0 },
{ "name":"Anibal Thiago Bezerra", "idlattes":"8478305453281130", "rotulo":"[Sem rotulo]", "collaborationrank":0.15000000596 },
{ "name":"Cassius Anderson Miquele de Melo", "idlattes":"4002033080997386", "rotulo":"[Sem rotulo]", "collaborationrank":1.0 },
{ "name":"Erico Goulart de Oliveira Costa", "idlattes":"4937965723746020", "rotulo":"[Sem rotulo]", "collaborationrank":0.15000000596 },
{ "name":"Fernando Goncalves Gardim", "idlattes":"2425549033248106", "rotulo":"[Sem rotulo]", "collaborationrank":0.15000000596 },
{ "name":"Gustavo do Amaral Valdiviesso", "idlattes":"4023778019418442", "rotulo":"[Sem rotulo]", "collaborationrank":0.15000000596 },
{ "name":"Heron Carlos de Godoy Caldas", "idlattes":"1373657423991547", "rotulo":"[Sem rotulo]", "collaborationrank":1.16102099419 },
{ "name":"Humberto Cesar Fernandes Lemos", "idlattes":"8374281747074655", "rotulo":"[Sem rotulo]", "collaborationrank":1.0 },
{ "name":"Ihosvany Camps Rodriguez", "idlattes":"3732563704810366", "rotulo":"[Sem rotulo]", "collaborationrank":0.15000000596 },
{ "name":"Marcelo Goncalves Vivas", "idlattes":"1312049227898761", "rotulo":"[Sem rotulo]", "collaborationrank":0.15000000596 },
{ "name":"Marcelo Martins de Oliveira", "idlattes":"2091568617999217", "rotulo":"[Sem rotulo]", "collaborationrank":0.849082767963 },
{ "name":"Rodrigo Rocha Cuzinatto", "idlattes":"8073303573679522", "rotulo":"[Sem rotulo]", "collaborationrank":1.0 },
{ "name":"Sidiney Geraldo Alves", "idlattes":"4536440727635518", "rotulo":"[Sem rotulo]", "collaborationrank":1.44165098667 },
{ "name":"Andre Luiz Mota", "idlattes":"8453016139576761", "rotulo":"[Sem rotulo]", "collaborationrank":1.35894048214 },
{ "name":"Leticia Ribeiro de Paiva", "idlattes":"9428416479663144", "rotulo":"[Sem rotulo]", "collaborationrank":0.709266245365 },
{ "name":"Lizardo Henrique Cerqueira Moreira Nunes", "idlattes":"9320579515635433", "rotulo":"[Sem rotulo]", "collaborationrank":0.480038493872 },
{ "name":"Mariama Rebello de Sousa Dias", "idlattes":"9972552337847809", "rotulo":"[Sem rotulo]", "collaborationrank":0.15000000596 }
],
"links":[
{ "source":0, "target":7, "value":2.0 },
{ "source":2, "target":11, "value":7.0 },
{ "source":6, "target":13, "value":11.0 },
{ "source":6, "target":15, "value":1.0 },
{ "source":10, "target":12, "value":5.0 },
{ "source":12, "target":14, "value":4.0 },
{ "source":13, "target":15, "value":3.0 }
]
}